README
setup.py
lorentz/__init__.py
lorentz.egg-info/PKG-INFO
lorentz.egg-info/SOURCES.txt
lorentz.egg-info/dependency_links.txt
lorentz.egg-info/top_level.txt