Metadata-Version: 1.0
Name: lorentz
Version: 0.0.1
Summary: simple python four vectors
Home-page: UNKNOWN
Author: Lukas Heinrich
Author-email: lukas.heinrich@gmail.com
License: UNKNOWN
Platform: UNKNOWN
